declust/__init__.py
declust/dbscan.py
declust/deconvolution.py
declust/hierarchical.py
declust/marker_selection.py
declust/preprocessing.py
declust/srg.py
declust/visualize.py
declust/scripts/__init__.py
declust/scripts/rtest1grp.R
declust-1.0.2.dist-info/METADATA
declust-1.0.2.dist-info/WHEEL
declust-1.0.2.dist-info/top_level.txt
declust-1.0.2.dist-info/RECORD
