Metadata-Version: 2.4
Name: declust
Version: 1.0.2
Summary: A cluster-based cell-type deconvolution of spatial transcriptomic data (DECLUST)
Home-page: https://github.com/Qingyueee/DECLUST
Author: Qingyue Wang
Author-email: qingyue.wang@hotmail.com
Classifier: Programming Language :: Python :: 3
Classifier: License :: OSI Approved :: GNU General Public License v3 (GPLv3)
Classifier: Operating System :: OS Independent
Requires-Python: >=3.9
Requires-Dist: matplotlib==3.7.5
Requires-Dist: numpy==1.24.4
Requires-Dist: pandas==2.0.3
Requires-Dist: scikit_learn==1.3.2
Requires-Dist: seaborn==0.13.2
